rtl/seq_matmul/seq_design.sv
// Sequential 3x3 matrix multiplier.
//
// A[0][0] = a[3:0],   A[0][1] = a[7:4], ..., A[2][2] = a[35:32]
// B uses the same layout.
// C[0][0] = c[11:0], C[0][1] = c[23:12], ..., C[2][2] = c[107:96]
//
// Pulse start for one clock cycle when busy is low.  The design performs
// k = 0, k = 1, and k = 2 on the next three clocks.  done is high for one
// clock cycle when c contains the completed matrix.

module matmul3x3_sequential (
    input  logic         clk,
    input  logic         rst,
    input  logic         start,
    input  logic [35:0]  a,
    input  logic [35:0]  b,
    output logic [107:0] c,
    output logic         busy,
    output logic         done
);

    logic [1:0] k;
    integer i, j;

    // Controller: accepts work, counts the three k values, and signals done.
    always_ff @(posedge clk) begin
        if (rst) begin
            k    <= 2'd0;
            busy <= 1'b0;
            done <= 1'b0;
        end else begin
            done <= 1'b0;

            if (start && !busy) begin
                k    <= 2'd0;
                busy <= 1'b1;
            end else if (busy) begin
                if (k == 2'd2) begin
                    busy <= 1'b0;
                    done <= 1'b1;
                end else begin
                    k <= k + 2'd1;
                end
            end
        end
    end

    // Datapath: clears or updates the nine result accumulators.
    always_ff @(posedge clk) begin
        if (rst) begin
            c <= '0;
        end else if (start && !busy) begin
            // Clear all accumulators before beginning a new matrix product.
            c <= '0;
        end else if (busy) begin
            for (i = 0; i < 3; i = i + 1) begin
                for (j = 0; j < 3; j = j + 1) begin
                    if (k == 2'd0) begin
                        // First multiply: start a fresh accumulator.
                        c[12 * (i * 3 + j) +: 12] <=
                            {8'd0, a[4 * (i * 3 + k) +: 4]}
                            * {8'd0, b[4 * (k * 3 + j) +: 4]};
                    end else begin
                        // Second and third multiplies: add to the sum.
                        c[12 * (i * 3 + j) +: 12] <=
                            c[12 * (i * 3 + j) +: 12]
                            + ({8'd0, a[4 * (i * 3 + k) +: 4]}
                            *  {8'd0, b[4 * (k * 3 + j) +: 4]});
                    end
                end
            end
        end
    end

endmodule

rtl/seq_matmul/seq_tb.sv
module tb_matmul3x3_sequential;

    logic         clk;
    logic         rst;
    logic         start;
    logic [35:0]  a;
    logic [35:0]  b;
    logic [107:0] c;
    logic         busy;
    logic         done;

    logic [107:0] expected;
    integer i, j;
    integer errors;

    matmul3x3_sequential dut (
        .clk(clk),
        .rst(rst),
        .start(start),
        .a(a),
        .b(b),
        .c(c),
        .busy(busy),
        .done(done)
    );

    // A 100 MHz clock: each period is 10 ns.
    always #5 clk = ~clk;

    initial begin
        $dumpfile("sequential_matmul.vcd");
        $dumpvars(0, tb_matmul3x3_sequential);

        clk   = 1'b0;
        rst   = 1'b1;
        start = 1'b0;

        // A = [1 2 3
        //      4 5 6
        //      7 8 9]
        a[ 3: 0] = 1;  a[ 7: 4] = 2;  a[11: 8] = 3;
        a[15:12] = 4;  a[19:16] = 5;  a[23:20] = 6;
        a[27:24] = 7;  a[31:28] = 8;  a[35:32] = 9;

        // B = [9 8 7
        //      6 5 4
        //      3 2 1]
        b[ 3: 0] = 9;  b[ 7: 4] = 8;  b[11: 8] = 7;
        b[15:12] = 6;  b[19:16] = 5;  b[23:20] = 4;
        b[27:24] = 3;  b[31:28] = 2;  b[35:32] = 1;

        // Expected C = [30  24  18
        //               84  69  54
        //              138 114  90]
        expected[ 11:  0] = 30;
        expected[ 23: 12] = 24;
        expected[ 35: 24] = 18;
        expected[ 47: 36] = 84;
        expected[ 59: 48] = 69;
        expected[ 71: 60] = 54;
        expected[ 83: 72] = 138;
        expected[ 95: 84] = 114;
        expected[107: 96] = 90;

        // Keep reset high for two rising clock edges.
        repeat (2) @(posedge clk);
        rst = 1'b0;

        // Pulse start for one clock cycle.
        @(negedge clk);
        start = 1'b1;
        @(posedge clk);
        #1 start = 1'b0;

        if (!busy) begin
            $display("FAIL: busy should be high after start.");
            $finish;
        end

        // Wait for the three k = 0, 1, 2 compute cycles.
        repeat (3) @(posedge clk);
        #1;

        errors = 0;

        if (!done) begin
            $display("FAIL: done should be high after three compute cycles.");
            errors = errors + 1;
        end

        if (busy) begin
            $display("FAIL: busy should be low when done is high.");
            errors = errors + 1;
        end

        for (i = 0; i < 3; i = i + 1) begin
            for (j = 0; j < 3; j = j + 1) begin
                if (c[12 * (i * 3 + j) +: 12]
                    !== expected[12 * (i * 3 + j) +: 12]) begin
                    $display("FAIL: C[%0d][%0d] = %0d, expected %0d",
                        i, j,
                        c[12 * (i * 3 + j) +: 12],
                        expected[12 * (i * 3 + j) +: 12]
                    );
                    errors = errors + 1;
                end
            end
        end

        @(posedge clk);
        #1;

        if (done) begin
            $display("FAIL: done should only be high for one clock cycle.");
            errors = errors + 1;
        end

        if (errors == 0)
            $display("PASS: sequential matrix multiplication is correct.");
        else
            $display("FAIL: %0d check(s) failed.", errors);

        $finish;
    end

endmodule

sequential_matmul.vcd
$date
	Mon Jul 13 01:05:39 2026
$end
$version
	Icarus Verilog
$end
$timescale
	1s
$end
$scope module tb_matmul3x3_sequential $end
$var wire 1 ! done $end
$var wire 108 " c [107:0] $end
$var wire 1 # busy $end
$var reg 36 $ a [35:0] $end
$var reg 36 % b [35:0] $end
$var reg 1 & clk $end
$var reg 108 ' expected [107:0] $end
$var reg 1 ( rst $end
$var reg 1 ) start $end
$var integer 32 * errors [31:0] $end
$var integer 32 + i [31:0] $end
$var integer 32 , j [31:0] $end
$scope module dut $end
$var wire 36 - a [35:0] $end
$var wire 36 . b [35:0] $end
$var wire 1 & clk $end
$var wire 1 ( rst $end
$var wire 1 ) start $end
$var reg 1 # busy $end
$var reg 108 / c [107:0] $end
$var reg 1 ! done $end
$var reg 2 0 k [1:0] $end
$var integer 32 1 i [31:0] $end
$var integer 32 2 j [31:0] $end
$upscope $end
$upscope $end
$enddefinitions $end
$comment Show the parameter values. $end
$dumpall
$end
#0
$dumpvars
bx 2
bx 1
bx 0
bx /
b100100011010001010110011110001001 .
b100110000111011001010100001100100001 -
bx ,
bx +
bx *
0)
1(
b1011010000001110010000010001010000000110110000001000101000001010100000000010010000000011000000000011110 '
0&
b100100011010001010110011110001001 %
b100110000111011001010100001100100001 $
x#
bx "
x!
$end
#5
0!
0#
b0 0
b0 "
b0 /
1&
#10
0&
#15
0(
1&
#20
1)
0&
#25
1#
1&
#26
0)
#30
0&
#35
b110001000000111000000000111111000000011100000000100000000000100100000000000111000000001000000000001001 "
b110001000000111000000000111111000000011100000000100000000000100100000000000111000000001000000000001001 /
b1 0
b11 2
b11 1
1&
#40
0&
#45
b10 0
b1010001000001100000000001101111000000110000000000111001000001000010000000001111000000010010000000010101 "
b1010001000001100000000001101111000000110000000000111001000001000010000000001111000000010010000000010101 /
b11 2
b11 1
1&
#50
0&
#55
b1011010000001110010000010001010000000110110000001000101000001010100000000010010000000011000000000011110 "
b1011010000001110010000010001010000000110110000001000101000001010100000000010010000000011000000000011110 /
1!
0#
b11 2
b11 1
1&
#56
b11 ,
b11 +
b0 *
#60
0&
#65
0!
1&
